{
    "cover": "https://static.hentaicdn.com/hentai/2330/1e/ccdn0001.jpg",
    "title": "Oppai Mamire",
    "genre": "Adult, Incest, Serialized, Shotacon",
    "author": "MAIHARA Matsuge",
    "chapter": "7",
    "backlink": "https://manganeet.com/post/oppai-mamire/",
    "images": [
      "https://static.hentaicdn.com/hentai/2330/1e/ccdn0185.jpg",
      "https://static.hentaicdn.com/hentai/2330/1e/ccdn0186.jpg",
      "https://static.hentaicdn.com/hentai/2330/1e/ccdn0187.jpg",
      "https://static.hentaicdn.com/hentai/2330/1e/ccdn0188.jpg",
      "https://static.hentaicdn.com/hentai/2330/1e/ccdn0189.jpg",
      "https://static.hentaicdn.com/hentai/2330/1e/ccdn0190.jpg",
      "https://static.hentaicdn.com/hentai/2330/1e/ccdn0191.jpg",
      "https://static.hentaicdn.com/hentai/2330/1e/ccdn0192.jpg",
      "https://static.hentaicdn.com/hentai/2330/1e/ccdn0193.jpg",
      "https://static.hentaicdn.com/hentai/2330/1e/ccdn0194.jpg",
      "https://static.hentaicdn.com/hentai/2330/1e/ccdn0195.jpg",
      "https://static.hentaicdn.com/hentai/2330/1e/ccdn0196.jpg",
      "https://static.hentaicdn.com/hentai/2330/1e/ccdn0197.jpg",
      "https://static.hentaicdn.com/hentai/2330/1e/ccdn0198.jpg",
      "https://static.hentaicdn.com/hentai/2330/1e/ccdn0199.jpg",
      "https://static.hentaicdn.com/hentai/2330/1e/ccdn0200.jpg",
      "https://static.hentaicdn.com/hentai/2330/1e/ccdn0201.jpg",
      "https://static.hentaicdn.com/hentai/2330/1e/ccdn0202.jpg",
      "https://static.hentaicdn.com/hentai/2330/1e/ccdn0203.jpg",
      "https://static.hentaicdn.com/hentai/2330/1e/ccdn0204.jpg",
      "https://static.hentaicdn.com/hentai/2330/1e/ccdn0205.jpg",
      "https://static.hentaicdn.com/hentai/2330/1e/ccdn0206.jpg",
      "https://static.hentaicdn.com/hentai/2330/1e/ccdn0207.jpg",
      "https://static.hentaicdn.com/hentai/2330/1e/ccdn0208.jpg"
    ]
  }